get_chromedriver.py
get_chromedriver-1.1.0.dist-info/LICENSE
get_chromedriver-1.1.0.dist-info/METADATA
get_chromedriver-1.1.0.dist-info/WHEEL
get_chromedriver-1.1.0.dist-info/top_level.txt
get_chromedriver-1.1.0.dist-info/RECORD
