Metadata-Version: 2.1
Name: get-chromedriver
Version: 1.1.0
Summary: Get the latest chromedriver for the chrome installed on your system
Home-page: https://github.com/dermasmid/get-chromedriver
Author: Cheskel Twersky
Author-email: twerskycheskel@gmail.com
License: MIT
Platform: UNKNOWN
Classifier: Programming Language :: Python :: 3
Classifier: License :: OSI Approved :: MIT License
Classifier: Operating System :: POSIX :: Linux
Requires-Python: >=3.6
Requires-Dist: requests
